dynamic_file_importer/__init__.py
dynamic_file_importer-0.1.5.dist-info/licenses/LICENSE
dynamic_file_importer-0.1.5.dist-info/METADATA
dynamic_file_importer-0.1.5.dist-info/WHEEL
dynamic_file_importer-0.1.5.dist-info/top_level.txt
dynamic_file_importer-0.1.5.dist-info/RECORD
