Metadata-Version: 2.4
Name: dynamic-file-importer
Version: 0.1.5
Summary: Treat a GitHub repo files as a Python object.
Author-email: Sten Leinasaar <stenleinasaar@proton.me>
License: MIT License
Project-URL: Homepage, https://github.com/StenLeinasaar/DynamicPromptImporter
Project-URL: Source, https://github.com/StenLeinasaar/DynamicPromptImporter
Project-URL: Issues, https://github.com/StenLeinasaar/DynamicPromptImporter/issues
Keywords: files,github,markdown
Classifier: License :: OSI Approved :: MIT License
Classifier: Programming Language :: Python :: 3
Classifier: Programming Language :: Python :: 3 :: Only
Classifier: Programming Language :: Python :: 3.9
Requires-Python: >=3.9
License-File: LICENSE
Requires-Dist: requests>=2.31
Dynamic: license-file
